CHANGES.txt
LICENSE.txt
MANIFEST.in
README.txt
TODO.txt
bootstrap.py
buildout.cfg
setup.py
eggs/WSGIProxy2-0.5.1-py3.10.egg/EGG-INFO/entry_points.txt
eggs/WSGIProxy2-0.5.1-py3.10.egg/EGG-INFO/requires.txt
eggs/WSGIProxy2-0.5.1-py3.10.egg/EGG-INFO/top_level.txt
eggs/WebOb-1.8.7-py3.10.egg/EGG-INFO/license.txt
eggs/WebOb-1.8.7-py3.10.egg/EGG-INFO/requires.txt
eggs/WebOb-1.8.7-py3.10.egg/EGG-INFO/top_level.txt
eggs/WebTest-2.0.35-py3.10.egg/EGG-INFO/entry_points.txt
eggs/WebTest-2.0.35-py3.10.egg/EGG-INFO/requires.txt
eggs/WebTest-2.0.35-py3.10.egg/EGG-INFO/top_level.txt
eggs/beautifulsoup4-4.13.4-py3.10.egg/EGG-INFO/requires.txt
eggs/beautifulsoup4-4.6.1-py3.10.egg/EGG-INFO/requires.txt
eggs/beautifulsoup4-4.6.1-py3.10.egg/EGG-INFO/top_level.txt
eggs/beautifulsoup4-4.9.3-py3.10.egg/EGG-INFO/COPYING.txt
eggs/beautifulsoup4-4.9.3-py3.10.egg/EGG-INFO/requires.txt
eggs/beautifulsoup4-4.9.3-py3.10.egg/EGG-INFO/top_level.txt
eggs/cffi-1.17.1-py3.10-win-amd64.egg/EGG-INFO/entry_points.txt
eggs/cffi-1.17.1-py3.10-win-amd64.egg/EGG-INFO/requires.txt
eggs/cffi-1.17.1-py3.10-win-amd64.egg/EGG-INFO/top_level.txt
eggs/coverage-7.10.4-py3.10.egg/EGG-INFO/entry_points.txt
eggs/coverage-7.10.4-py3.10.egg/EGG-INFO/requires.txt
eggs/coverage-7.10.4-py3.10.egg/EGG-INFO/top_level.txt
eggs/coverage-7.10.4-py3.10.egg/EGG-INFO/licenses/LICENSE.txt
eggs/future-1.0.0-py3.10.egg/EGG-INFO/LICENSE.txt
eggs/future-1.0.0-py3.10.egg/EGG-INFO/entry_points.txt
eggs/future-1.0.0-py3.10.egg/EGG-INFO/top_level.txt
eggs/lxml-4.9.4-py3.10-win-amd64.egg/EGG-INFO/LICENSE.txt
eggs/lxml-4.9.4-py3.10-win-amd64.egg/EGG-INFO/LICENSES.txt
eggs/lxml-4.9.4-py3.10-win-amd64.egg/EGG-INFO/requires.txt
eggs/lxml-4.9.4-py3.10-win-amd64.egg/EGG-INFO/top_level.txt
eggs/lxml-4.9.4-py3.10-win-amd64.egg/lxml/isoschematron/resources/xsl/iso-schematron-xslt1/readme.txt
eggs/multipart-1.3.0-py3.10.egg/EGG-INFO/requires.txt
eggs/p01.checker-0.5.12-py3.10.egg/EGG-INFO/SOURCES.txt
eggs/p01.checker-0.5.12-py3.10.egg/EGG-INFO/dependency_links.txt
eggs/p01.checker-0.5.12-py3.10.egg/EGG-INFO/namespace_packages.txt
eggs/p01.checker-0.5.12-py3.10.egg/EGG-INFO/requires.txt
eggs/p01.checker-0.5.12-py3.10.egg/EGG-INFO/top_level.txt
eggs/p01.checker-0.5.12-py3.10.egg/p01/checker/checker.txt
eggs/p01.checker-0.5.12-py3.10.egg/p01/checker/sample/tab.txt
eggs/p01.json-0.7.2-py3.10.egg/EGG-INFO/SOURCES.txt
eggs/p01.json-0.7.2-py3.10.egg/EGG-INFO/dependency_links.txt
eggs/p01.json-0.7.2-py3.10.egg/EGG-INFO/namespace_packages.txt
eggs/p01.json-0.7.2-py3.10.egg/EGG-INFO/requires.txt
eggs/p01.json-0.7.2-py3.10.egg/EGG-INFO/top_level.txt
eggs/p01.json-0.7.2-py3.10.egg/p01/json/README.txt
eggs/p01.jsonrpc-0.8.0-py3.10.egg/EGG-INFO/SOURCES.txt
eggs/p01.jsonrpc-0.8.0-py3.10.egg/EGG-INFO/dependency_links.txt
eggs/p01.jsonrpc-0.8.0-py3.10.egg/EGG-INFO/namespace_packages.txt
eggs/p01.jsonrpc-0.8.0-py3.10.egg/EGG-INFO/requires.txt
eggs/p01.jsonrpc-0.8.0-py3.10.egg/EGG-INFO/top_level.txt
eggs/p01.jsonrpc-0.8.0-py3.10.egg/p01/jsonrpc/README.txt
eggs/p01.jsonrpc-0.8.0-py3.10.egg/p01/jsonrpc/zcml.txt
eggs/p01.jsonrpc-0.8.1-py3.10.egg/EGG-INFO/SOURCES.txt
eggs/p01.jsonrpc-0.8.1-py3.10.egg/EGG-INFO/dependency_links.txt
eggs/p01.jsonrpc-0.8.1-py3.10.egg/EGG-INFO/namespace_packages.txt
eggs/p01.jsonrpc-0.8.1-py3.10.egg/EGG-INFO/requires.txt
eggs/p01.jsonrpc-0.8.1-py3.10.egg/EGG-INFO/top_level.txt
eggs/p01.jsonrpc-0.8.1-py3.10.egg/p01/jsonrpc/README.txt
eggs/p01.jsonrpc-0.8.1-py3.10.egg/p01/jsonrpc/zcml.txt
eggs/persistent-6.1.1-py3.10-win-amd64.egg/EGG-INFO/LICENSE.txt
eggs/persistent-6.1.1-py3.10-win-amd64.egg/EGG-INFO/requires.txt
eggs/persistent-6.1.1-py3.10-win-amd64.egg/EGG-INFO/top_level.txt
eggs/polib-1.2.0-py3.10.egg/EGG-INFO/top_level.txt
eggs/pycparser-2.22-py3.10.egg/EGG-INFO/top_level.txt
eggs/pyflakes-2.1.1-py3.10.egg/EGG-INFO/entry_points.txt
eggs/pyflakes-2.1.1-py3.10.egg/EGG-INFO/top_level.txt
eggs/pyflakes-3.4.0-py3.10.egg/EGG-INFO/entry_points.txt
eggs/pyflakes-3.4.0-py3.10.egg/EGG-INFO/top_level.txt
eggs/python_gettext-5.0-py3.10.egg/EGG-INFO/top_level.txt
eggs/pytz-2025.2-py3.10.egg/EGG-INFO/LICENSE.txt
eggs/pytz-2025.2-py3.10.egg/EGG-INFO/top_level.txt
eggs/sgmllib3k-1.0.0-py3.10.egg/EGG-INFO/SOURCES.txt
eggs/sgmllib3k-1.0.0-py3.10.egg/EGG-INFO/dependency_links.txt
eggs/sgmllib3k-1.0.0-py3.10.egg/EGG-INFO/top_level.txt
eggs/six-1.17.0-py3.10.egg/EGG-INFO/top_level.txt
eggs/soupsieve-1.9.6-py3.10.egg/EGG-INFO/top_level.txt
eggs/transaction-5.0-py3.10.egg/EGG-INFO/LICENSE.txt
eggs/transaction-5.0-py3.10.egg/EGG-INFO/requires.txt
eggs/transaction-5.0-py3.10.egg/EGG-INFO/top_level.txt
eggs/waitress-3.0.2-py3.10.egg/EGG-INFO/LICENSE.txt
eggs/waitress-3.0.2-py3.10.egg/EGG-INFO/entry_points.txt
eggs/waitress-3.0.2-py3.10.egg/EGG-INFO/requires.txt
eggs/waitress-3.0.2-py3.10.egg/EGG-INFO/top_level.txt
eggs/z3c.coverage-2.1.0-py3.10.egg/EGG-INFO/SOURCES.txt
eggs/z3c.coverage-2.1.0-py3.10.egg/EGG-INFO/dependency_links.txt
eggs/z3c.coverage-2.1.0-py3.10.egg/EGG-INFO/entry_points.txt
eggs/z3c.coverage-2.1.0-py3.10.egg/EGG-INFO/namespace_packages.txt
eggs/z3c.coverage-2.1.0-py3.10.egg/EGG-INFO/requires.txt
eggs/z3c.coverage-2.1.0-py3.10.egg/EGG-INFO/top_level.txt
eggs/z3c.coverage-2.1.0-py3.10.egg/z3c/coverage/README.txt
eggs/z3c.coverage-2.1.0-py3.10.egg/z3c/coverage/coveragediff.txt
eggs/z3c.coverage-2.1.0-py3.10.egg/z3c/coverage/sampleinput/decoy.txt
eggs/zc.recipe.egg-2.0.7-py3.10.egg/EGG-INFO/SOURCES.txt
eggs/zc.recipe.egg-2.0.7-py3.10.egg/EGG-INFO/dependency_links.txt
eggs/zc.recipe.egg-2.0.7-py3.10.egg/EGG-INFO/entry_points.txt
eggs/zc.recipe.egg-2.0.7-py3.10.egg/EGG-INFO/namespace_packages.txt
eggs/zc.recipe.egg-2.0.7-py3.10.egg/EGG-INFO/requires.txt
eggs/zc.recipe.egg-2.0.7-py3.10.egg/EGG-INFO/top_level.txt
eggs/zc.recipe.testrunner-3.2-py3.10.egg/EGG-INFO/LICENSE.txt
eggs/zc.recipe.testrunner-3.2-py3.10.egg/EGG-INFO/entry_points.txt
eggs/zc.recipe.testrunner-3.2-py3.10.egg/EGG-INFO/namespace_packages.txt
eggs/zc.recipe.testrunner-3.2-py3.10.egg/EGG-INFO/requires.txt
